bacalhau_airflow/__init__.py
bacalhau_airflow/hooks.py
bacalhau_airflow/operators.py
bacalhau_airflow-1.3.2.dist-info/LICENSE
bacalhau_airflow-1.3.2.dist-info/METADATA
bacalhau_airflow-1.3.2.dist-info/WHEEL
bacalhau_airflow-1.3.2.dist-info/top_level.txt
bacalhau_airflow-1.3.2.dist-info/RECORD
