Metadata-Version: 2.1
Name: bacalhau-airflow
Version: 1.3.2
Summary: An Apache Airflow provider for Bacalhau.
Home-page: https://github.com/filecoin-project/bacalhau/tree/main/integration/airflow
Author: Enrico Rotundo
Author-email: team@bacalhau.org
License: Apache Software License 2.0
Keywords: bacalhau,airflow,provider
Classifier: Development Status :: 2 - Pre-Alpha
Classifier: Intended Audience :: Developers
Classifier: License :: OSI Approved :: Apache Software License
Classifier: Natural Language :: English
Classifier: Programming Language :: Python :: 3
Classifier: Programming Language :: Python :: 3.8
Requires-Python: >=3.8
License-File: LICENSE
Requires-Dist: bacalhau-sdk
Requires-Dist: apache-airflow >=2.3.0
